{
  "session_info": {
    "session_id": "SESSION_FILE_10_254_2_40_1st_batch_20250621_112155",
    "hostname": "10_254_2_40",
    "instance_id": "velquc",
    "start_time": "2025-06-21T11:21:55.518607",
    "end_time": "2025-06-21T11:32:47.461140",
    "session_type": "COMPREHENSIVE_SCAN",
    "range_start": "FILE_BASED",
    "range_end": "FILE_BASED",
    "scanner_version": "2.1_session_logging"
  },
  "testing_results": [
    {
      "slug": "ehcib",
      "timestamp": "2025-06-21T11:22:10.321858",
      "test_type": "COMPREHENSIVE_SCAN",
      "status": "INACTIVE_401",
      "business_name": "",
      "load_time": 13.241644144058228,
      "content_length": 49,
      "business_indicators": 0,
      "error_indicators": 4,
      "final_url": "https://vsdigital-bookingwidget-prod.azurewebsites.net/widget/401",
      "error": ""
    },
    {
      "slug": "m4r3a",
      "timestamp": "2025-06-21T11:22:25.107095",
      "test_type": "COMPREHENSIVE_SCAN",
      "status": "INACTIVE_401",
      "business_name": "",
      "load_time": 13.563914060592651,
      "content_length": 49,
      "business_indicators": 0,
      "error_indicators": 4,
      "final_url": "https://vsdigital-bookingwidget-prod.azurewebsites.net/widget/401",
      "error": ""
    },
    {
      "slug": "y2s5e",
      "timestamp": "2025-06-21T11:22:40.348155",
      "test_type": "COMPREHENSIVE_SCAN",
      "status": "INACTIVE_401",
      "business_name": "",
      "load_time": 13.970960140228271,
      "content_length": 49,
      "business_indicators": 0,
      "error_indicators": 4,
      "final_url": "https://vsdigital-bookingwidget-prod.azurewebsites.net/widget/401",
      "error": ""
    },
    {
      "slug": "3dd0i",
      "timestamp": "2025-06-21T11:22:54.760939",
      "test_type": "COMPREHENSIVE_SCAN",
      "status": "INACTIVE_401",
      "business_name": "",
      "load_time": 13.182092905044556,
      "content_length": 49,
      "business_indicators": 0,
      "error_indicators": 4,
      "final_url": "https://vsdigital-bookingwidget-prod.azurewebsites.net/widget/401",
      "error": ""
    },
    {
      "slug": "s2096",
      "timestamp": "2025-06-21T11:23:09.023870",
      "test_type": "COMPREHENSIVE_SCAN",
      "status": "INACTIVE_401",
      "business_name": "",
      "load_time": 13.041566133499146,
      "content_length": 49,
      "business_indicators": 0,
      "error_indicators": 4,
      "final_url": "https://vsdigital-bookingwidget-prod.azurewebsites.net/widget/401",
      "error": ""
    },
    {
      "slug": "tjgvt",
      "timestamp": "2025-06-21T11:23:25.078530",
      "test_type": "COMPREHENSIVE_SCAN",
      "status": "INACTIVE_401",
      "business_name": "",
      "load_time": 14.80689287185669,
      "content_length": 49,
      "business_indicators": 0,
      "error_indicators": 4,
      "final_url": "https://vsdigital-bookingwidget-prod.azurewebsites.net/widget/401",
      "error": ""
    },
    {
      "slug": "6erb5",
      "timestamp": "2025-06-21T11:23:39.216558",
      "test_type": "COMPREHENSIVE_SCAN",
      "status": "INACTIVE_401",
      "business_name": "",
      "load_time": 12.865161895751953,
      "content_length": 49,
      "business_indicators": 0,
      "error_indicators": 4,
      "final_url": "https://vsdigital-bookingwidget-prod.azurewebsites.net/widget/401",
      "error": ""
    },
    {
      "slug": "zi3ha",
      "timestamp": "2025-06-21T11:23:54.142591",
      "test_type": "COMPREHENSIVE_SCAN",
      "status": "INACTIVE_401",
      "business_name": "",
      "load_time": 13.685866117477417,
      "content_length": 49,
      "business_indicators": 0,
      "error_indicators": 4,
      "final_url": "https://vsdigital-bookingwidget-prod.azurewebsites.net/widget/401",
      "error": ""
    },
    {
      "slug": "mq59u",
      "timestamp": "2025-06-21T11:24:08.839802",
      "test_type": "COMPREHENSIVE_SCAN",
      "status": "INACTIVE_401",
      "business_name": "",
      "load_time": 13.463410139083862,
      "content_length": 49,
      "business_indicators": 0,
      "error_indicators": 4,
      "final_url": "https://vsdigital-bookingwidget-prod.azurewebsites.net/widget/401",
      "error": ""
    },
    {
      "slug": "wi37f",
      "timestamp": "2025-06-21T11:24:23.277221",
      "test_type": "COMPREHENSIVE_SCAN",
      "status": "INACTIVE_401",
      "business_name": "",
      "load_time": 13.173294067382812,
      "content_length": 49,
      "business_indicators": 0,
      "error_indicators": 4,
      "final_url": "https://vsdigital-bookingwidget-prod.azurewebsites.net/widget/401",
      "error": ""
    },
    {
      "slug": "xm32m",
      "timestamp": "2025-06-21T11:24:42.103472",
      "test_type": "COMPREHENSIVE_SCAN",
      "status": "INACTIVE_401",
      "business_name": "",
      "load_time": 17.580649852752686,
      "content_length": 49,
      "business_indicators": 0,
      "error_indicators": 4,
      "final_url": "https://vsdigital-bookingwidget-prod.azurewebsites.net/widget/401",
      "error": ""
    },
    {
      "slug": "9844g",
      "timestamp": "2025-06-21T11:24:57.083658",
      "test_type": "COMPREHENSIVE_SCAN",
      "status": "INACTIVE_401",
      "business_name": "",
      "load_time": 13.750064134597778,
      "content_length": 49,
      "business_indicators": 0,
      "error_indicators": 4,
      "final_url": "https://vsdigital-bookingwidget-prod.azurewebsites.net/widget/401",
      "error": ""
    },
    {
      "slug": "0wsw1",
      "timestamp": "2025-06-21T11:25:12.821039",
      "test_type": "COMPREHENSIVE_SCAN",
      "status": "INACTIVE_401",
      "business_name": "",
      "load_time": 14.48994517326355,
      "content_length": 49,
      "business_indicators": 0,
      "error_indicators": 4,
      "final_url": "https://vsdigital-bookingwidget-prod.azurewebsites.net/widget/401",
      "error": ""
    },
    {
      "slug": "rwj91",
      "timestamp": "2025-06-21T11:25:27.775375",
      "test_type": "COMPREHENSIVE_SCAN",
      "status": "INACTIVE_401",
      "business_name": "",
      "load_time": 13.718374013900757,
      "content_length": 49,
      "business_indicators": 0,
      "error_indicators": 4,
      "final_url": "https://vsdigital-bookingwidget-prod.azurewebsites.net/widget/401",
      "error": ""
    },
    {
      "slug": "y7u9i",
      "timestamp": "2025-06-21T11:25:42.234926",
      "test_type": "COMPREHENSIVE_SCAN",
      "status": "INACTIVE_401",
      "business_name": "",
      "load_time": 13.207322120666504,
      "content_length": 49,
      "business_indicators": 0,
      "error_indicators": 4,
      "final_url": "https://vsdigital-bookingwidget-prod.azurewebsites.net/widget/401",
      "error": ""
    },
    {
      "slug": "mm8wf",
      "timestamp": "2025-06-21T11:25:57.326697",
      "test_type": "COMPREHENSIVE_SCAN",
      "status": "INACTIVE_401",
      "business_name": "",
      "load_time": 13.846553802490234,
      "content_length": 49,
      "business_indicators": 0,
      "error_indicators": 4,
      "final_url": "https://vsdigital-bookingwidget-prod.azurewebsites.net/widget/401",
      "error": ""
    },
    {
      "slug": "vn92m",
      "timestamp": "2025-06-21T11:26:12.208595",
      "test_type": "COMPREHENSIVE_SCAN",
      "status": "INACTIVE_401",
      "business_name": "",
      "load_time": 13.657055377960205,
      "content_length": 49,
      "business_indicators": 0,
      "error_indicators": 4,
      "final_url": "https://vsdigital-bookingwidget-prod.azurewebsites.net/widget/401",
      "error": ""
    },
    {
      "slug": "1yv9l",
      "timestamp": "2025-06-21T11:26:27.146729",
      "test_type": "COMPREHENSIVE_SCAN",
      "status": "INACTIVE_401",
      "business_name": "",
      "load_time": 13.713188171386719,
      "content_length": 49,
      "business_indicators": 0,
      "error_indicators": 4,
      "final_url": "https://vsdigital-bookingwidget-prod.azurewebsites.net/widget/401",
      "error": ""
    },
    {
      "slug": "pwhf5",
      "timestamp": "2025-06-21T11:26:43.026254",
      "test_type": "COMPREHENSIVE_SCAN",
      "status": "INACTIVE_401",
      "business_name": "",
      "load_time": 14.643857955932617,
      "content_length": 49,
      "business_indicators": 0,
      "error_indicators": 4,
      "final_url": "https://vsdigital-bookingwidget-prod.azurewebsites.net/widget/401",
      "error": ""
    },
    {
      "slug": "087sk",
      "timestamp": "2025-06-21T11:26:58.065121",
      "test_type": "COMPREHENSIVE_SCAN",
      "status": "INACTIVE_401",
      "business_name": "",
      "load_time": 13.846693277359009,
      "content_length": 49,
      "business_indicators": 0,
      "error_indicators": 4,
      "final_url": "https://vsdigital-bookingwidget-prod.azurewebsites.net/widget/401",
      "error": ""
    },
    {
      "slug": "0g10f",
      "timestamp": "2025-06-21T11:27:12.864676",
      "test_type": "COMPREHENSIVE_SCAN",
      "status": "INACTIVE_401",
      "business_name": "",
      "load_time": 13.556709051132202,
      "content_length": 49,
      "business_indicators": 0,
      "error_indicators": 4,
      "final_url": "https://vsdigital-bookingwidget-prod.azurewebsites.net/widget/401",
      "error": ""
    },
    {
      "slug": "4o4dg",
      "timestamp": "2025-06-21T11:27:27.704948",
      "test_type": "COMPREHENSIVE_SCAN",
      "status": "INACTIVE_401",
      "business_name": "",
      "load_time": 13.581677913665771,
      "content_length": 49,
      "business_indicators": 0,
      "error_indicators": 4,
      "final_url": "https://vsdigital-bookingwidget-prod.azurewebsites.net/widget/401",
      "error": ""
    },
    {
      "slug": "6dt9t",
      "timestamp": "2025-06-21T11:27:42.282040",
      "test_type": "COMPREHENSIVE_SCAN",
      "status": "INACTIVE_401",
      "business_name": "",
      "load_time": 13.329189777374268,
      "content_length": 49,
      "business_indicators": 0,
      "error_indicators": 4,
      "final_url": "https://vsdigital-bookingwidget-prod.azurewebsites.net/widget/401",
      "error": ""
    },
    {
      "slug": "lr61a",
      "timestamp": "2025-06-21T11:27:56.421209",
      "test_type": "COMPREHENSIVE_SCAN",
      "status": "INACTIVE_401",
      "business_name": "",
      "load_time": 12.935070991516113,
      "content_length": 49,
      "business_indicators": 0,
      "error_indicators": 4,
      "final_url": "https://vsdigital-bookingwidget-prod.azurewebsites.net/widget/401",
      "error": ""
    },
    {
      "slug": "1c34x",
      "timestamp": "2025-06-21T11:28:12.735328",
      "test_type": "COMPREHENSIVE_SCAN",
      "status": "INACTIVE_401",
      "business_name": "",
      "load_time": 15.071080207824707,
      "content_length": 49,
      "business_indicators": 0,
      "error_indicators": 4,
      "final_url": "https://vsdigital-bookingwidget-prod.azurewebsites.net/widget/401",
      "error": ""
    },
    {
      "slug": "bdtvx",
      "timestamp": "2025-06-21T11:28:27.961560",
      "test_type": "COMPREHENSIVE_SCAN",
      "status": "INACTIVE_401",
      "business_name": "",
      "load_time": 14.014416933059692,
      "content_length": 49,
      "business_indicators": 0,
      "error_indicators": 4,
      "final_url": "https://vsdigital-bookingwidget-prod.azurewebsites.net/widget/401",
      "error": ""
    },
    {
      "slug": "ym407",
      "timestamp": "2025-06-21T11:28:42.414540",
      "test_type": "COMPREHENSIVE_SCAN",
      "status": "INACTIVE_401",
      "business_name": "",
      "load_time": 13.230755090713501,
      "content_length": 49,
      "business_indicators": 0,
      "error_indicators": 4,
      "final_url": "https://vsdigital-bookingwidget-prod.azurewebsites.net/widget/401",
      "error": ""
    },
    {
      "slug": "zt90o",
      "timestamp": "2025-06-21T11:29:01.380043",
      "test_type": "COMPREHENSIVE_SCAN",
      "status": "INACTIVE_401",
      "business_name": "",
      "load_time": 17.742762088775635,
      "content_length": 49,
      "business_indicators": 0,
      "error_indicators": 4,
      "final_url": "https://vsdigital-bookingwidget-prod.azurewebsites.net/widget/401",
      "error": ""
    },
    {
      "slug": "mnsbl",
      "timestamp": "2025-06-21T11:29:16.732373",
      "test_type": "COMPREHENSIVE_SCAN",
      "status": "INACTIVE_401",
      "business_name": "",
      "load_time": 14.034186840057373,
      "content_length": 49,
      "business_indicators": 0,
      "error_indicators": 4,
      "final_url": "https://vsdigital-bookingwidget-prod.azurewebsites.net/widget/401",
      "error": ""
    },
    {
      "slug": "nc53q",
      "timestamp": "2025-06-21T11:29:31.495355",
      "test_type": "COMPREHENSIVE_SCAN",
      "status": "INACTIVE_401",
      "business_name": "",
      "load_time": 13.436032056808472,
      "content_length": 49,
      "business_indicators": 0,
      "error_indicators": 4,
      "final_url": "https://vsdigital-bookingwidget-prod.azurewebsites.net/widget/401",
      "error": ""
    },
    {
      "slug": "b3zhy",
      "timestamp": "2025-06-21T11:29:46.307527",
      "test_type": "COMPREHENSIVE_SCAN",
      "status": "INACTIVE_401",
      "business_name": "",
      "load_time": 13.567335367202759,
      "content_length": 49,
      "business_indicators": 0,
      "error_indicators": 4,
      "final_url": "https://vsdigital-bookingwidget-prod.azurewebsites.net/widget/401",
      "error": ""
    },
    {
      "slug": "b97nj",
      "timestamp": "2025-06-21T11:30:01.005836",
      "test_type": "COMPREHENSIVE_SCAN",
      "status": "INACTIVE_401",
      "business_name": "",
      "load_time": 13.370939016342163,
      "content_length": 49,
      "business_indicators": 0,
      "error_indicators": 4,
      "final_url": "https://vsdigital-bookingwidget-prod.azurewebsites.net/widget/401",
      "error": ""
    },
    {
      "slug": "yg097",
      "timestamp": "2025-06-21T11:30:16.038742",
      "test_type": "COMPREHENSIVE_SCAN",
      "status": "INACTIVE_401",
      "business_name": "",
      "load_time": 13.638613939285278,
      "content_length": 49,
      "business_indicators": 0,
      "error_indicators": 4,
      "final_url": "https://vsdigital-bookingwidget-prod.azurewebsites.net/widget/401",
      "error": ""
    },
    {
      "slug": "bdysa",
      "timestamp": "2025-06-21T11:30:30.362567",
      "test_type": "COMPREHENSIVE_SCAN",
      "status": "INACTIVE_401",
      "business_name": "",
      "load_time": 13.058957815170288,
      "content_length": 49,
      "business_indicators": 0,
      "error_indicators": 4,
      "final_url": "https://vsdigital-bookingwidget-prod.azurewebsites.net/widget/401",
      "error": ""
    },
    {
      "slug": "muwq0",
      "timestamp": "2025-06-21T11:30:44.936216",
      "test_type": "COMPREHENSIVE_SCAN",
      "status": "INACTIVE_401",
      "business_name": "",
      "load_time": 13.336351871490479,
      "content_length": 49,
      "business_indicators": 0,
      "error_indicators": 4,
      "final_url": "https://vsdigital-bookingwidget-prod.azurewebsites.net/widget/401",
      "error": ""
    },
    {
      "slug": "mg09w",
      "timestamp": "2025-06-21T11:31:00.468955",
      "test_type": "COMPREHENSIVE_SCAN",
      "status": "INACTIVE_401",
      "business_name": "",
      "load_time": 14.271980047225952,
      "content_length": 49,
      "business_indicators": 0,
      "error_indicators": 4,
      "final_url": "https://vsdigital-bookingwidget-prod.azurewebsites.net/widget/401",
      "error": ""
    },
    {
      "slug": "bch84",
      "timestamp": "2025-06-21T11:31:15.987460",
      "test_type": "COMPREHENSIVE_SCAN",
      "status": "INACTIVE_401",
      "business_name": "",
      "load_time": 14.256815910339355,
      "content_length": 49,
      "business_indicators": 0,
      "error_indicators": 4,
      "final_url": "https://vsdigital-bookingwidget-prod.azurewebsites.net/widget/401",
      "error": ""
    },
    {
      "slug": "lt07m",
      "timestamp": "2025-06-21T11:31:30.764584",
      "test_type": "COMPREHENSIVE_SCAN",
      "status": "INACTIVE_401",
      "business_name": "",
      "load_time": 13.53918981552124,
      "content_length": 49,
      "business_indicators": 0,
      "error_indicators": 4,
      "final_url": "https://vsdigital-bookingwidget-prod.azurewebsites.net/widget/401",
      "error": ""
    },
    {
      "slug": "yca1h",
      "timestamp": "2025-06-21T11:31:46.148851",
      "test_type": "COMPREHENSIVE_SCAN",
      "status": "INACTIVE_401",
      "business_name": "",
      "load_time": 14.14146876335144,
      "content_length": 49,
      "business_indicators": 0,
      "error_indicators": 4,
      "final_url": "https://vsdigital-bookingwidget-prod.azurewebsites.net/widget/401",
      "error": ""
    },
    {
      "slug": "bb49u",
      "timestamp": "2025-06-21T11:32:01.406042",
      "test_type": "COMPREHENSIVE_SCAN",
      "status": "INACTIVE_401",
      "business_name": "",
      "load_time": 14.075978994369507,
      "content_length": 49,
      "business_indicators": 0,
      "error_indicators": 4,
      "final_url": "https://vsdigital-bookingwidget-prod.azurewebsites.net/widget/401",
      "error": ""
    },
    {
      "slug": "mm7ar",
      "timestamp": "2025-06-21T11:32:15.437805",
      "test_type": "COMPREHENSIVE_SCAN",
      "status": "INACTIVE_401",
      "business_name": "",
      "load_time": 12.800309181213379,
      "content_length": 49,
      "business_indicators": 0,
      "error_indicators": 4,
      "final_url": "https://vsdigital-bookingwidget-prod.azurewebsites.net/widget/401",
      "error": ""
    },
    {
      "slug": "pzra0",
      "timestamp": "2025-06-21T11:32:30.397366",
      "test_type": "COMPREHENSIVE_SCAN",
      "status": "INACTIVE_401",
      "business_name": "",
      "load_time": 13.555371046066284,
      "content_length": 49,
      "business_indicators": 0,
      "error_indicators": 4,
      "final_url": "https://vsdigital-bookingwidget-prod.azurewebsites.net/widget/401",
      "error": ""
    },
    {
      "slug": "0z99u",
      "timestamp": "2025-06-21T11:32:45.275552",
      "test_type": "COMPREHENSIVE_SCAN",
      "status": "INACTIVE_401",
      "business_name": "",
      "load_time": 13.450131893157959,
      "content_length": 49,
      "business_indicators": 0,
      "error_indicators": 4,
      "final_url": "https://vsdigital-bookingwidget-prod.azurewebsites.net/widget/401",
      "error": ""
    }
  ],
  "session_summary": {
    "total_tested": 86,
    "active_found": 0,
    "inactive_found": 86,
    "connection_errors": 0,
    "browser_errors": 0,
    "other_errors": 0,
    "session_duration_seconds": 651.942533,
    "average_test_time": 7.580727127906977
  }
}